AsyncioUtils/AsyncioUtils.py
AsyncioUtils/__init__.py
robotframework_asyncio_utils-0.2.0.dist-info/METADATA
robotframework_asyncio_utils-0.2.0.dist-info/WHEEL
robotframework_asyncio_utils-0.2.0.dist-info/licenses/LICENSE
robotframework_asyncio_utils-0.2.0.dist-info/RECORD
