Metadata-Version: 2.4
Name: robotframework-asyncio-utils
Version: 0.2.0
Summary: Some keywords to help with async programming in robot framework
Project-URL: Homepage, https://github.com/ygorpontelo/robot-asyncio-utils
Author-email: Ygor Pontelo <ygorpontelo@gmail.com>
License-Expression: MIT
License-File: LICENSE
Keywords: async,utils
Classifier: Framework :: Robot Framework
Requires-Python: >=3.8
Requires-Dist: robotframework>=6.1.1
